graph_ltpl/Graph_LTPL.py
graph_ltpl/__init__.py
graph_ltpl/data_objects/GraphBase.py
graph_ltpl/data_objects/ObjectListInterface.py
graph_ltpl/data_objects/__init__.py
graph_ltpl/helper_funcs/__init__.py
graph_ltpl/helper_funcs/src/Logging.py
graph_ltpl/helper_funcs/src/__init__.py
graph_ltpl/helper_funcs/src/calc_brake_emergency.py
graph_ltpl/helper_funcs/src/calc_vel_profile_follow.py
graph_ltpl/helper_funcs/src/closest_path_index.py
graph_ltpl/helper_funcs/src/get_s_coord.py
graph_ltpl/imp_global_traj/__init__.py
graph_ltpl/imp_global_traj/src/__init__.py
graph_ltpl/imp_global_traj/src/import_globtraj_csv.py
graph_ltpl/imp_global_traj/src/variable_step_size.py
graph_ltpl/offline_graph/__init__.py
graph_ltpl/offline_graph/src/__init__.py
graph_ltpl/offline_graph/src/gen_edges.py
graph_ltpl/offline_graph/src/gen_node_skeleton.py
graph_ltpl/offline_graph/src/gen_offline_cost.py
graph_ltpl/offline_graph/src/main_offline_callback.py
graph_ltpl/offline_graph/src/prune_graph.py
graph_ltpl/online_graph/__init__.py
graph_ltpl/online_graph/src/OnlineTrajectoryHandler.py
graph_ltpl/online_graph/src/VpForwardBackward.py
graph_ltpl/online_graph/src/VpSQP.py
graph_ltpl/online_graph/src/__init__.py
graph_ltpl/online_graph/src/check_inside_bounds.py
graph_ltpl/online_graph/src/gen_local_node_template.py
graph_ltpl/online_graph/src/get_intersec_edges.py
graph_ltpl/online_graph/src/get_zone_nodes.py
graph_ltpl/online_graph/src/main_online_path_gen.py
graph_ltpl/testing_tools/__init__.py
graph_ltpl/testing_tools/src/__init__.py
graph_ltpl/testing_tools/src/objectlist_dummy.py
graph_ltpl/testing_tools/src/vdc_dummy.py
graph_ltpl/visualization/__init__.py
graph_ltpl/visualization/src/PlotHandler.py
graph_ltpl/visualization/src/__init__.py
graph_ltpl/visualization/src/visualize_graph_log.py
graph_ltpl-0.48.dist-info/METADATA
graph_ltpl-0.48.dist-info/WHEEL
graph_ltpl-0.48.dist-info/top_level.txt
graph_ltpl-0.48.dist-info/RECORD
