Metadata-Version: 2.1
Name: graph-ltpl
Version: 0.48
Summary: Multilayer graph-based local trajectory planner.
Home-page: UNKNOWN
Author: Tim Stahl
Author-email: stahl@ftm.mw.tum.de
License: UNKNOWN
Platform: UNKNOWN
Classifier: Programming Language :: Python :: 3
Classifier: Programming Language :: Python :: 3.5
Classifier: Programming Language :: Python :: 3.6
Classifier: Programming Language :: Python :: 3.7
Classifier: License :: OSI Approved :: GNU Lesser General Public License v3 (LGPLv3)
Classifier: Operating System :: OS Independent
Requires-Dist: numpy (==1.18.1)
Requires-Dist: matplotlib (==3.3.1)
Requires-Dist: scipy (==1.3.3)
Requires-Dist: python-igraph (==0.8.2)
Requires-Dist: trajectory-planning-helpers (==0.75)
